CHANGELOG.md
LICENSE
MANIFEST.in
README.md
setup.py
man/man1/obis-addref.1
man/man1/obis-clone.1
man/man1/obis-collection.1
man/man1/obis-commit.1
man/man1/obis-config.1
man/man1/obis-data_set.1
man/man1/obis-download.1
man/man1/obis-init.1
man/man1/obis-init_analysis.1
man/man1/obis-move.1
man/man1/obis-object.1
man/man1/obis-removeref.1
man/man1/obis-repository.1
man/man1/obis-settings.1
man/man1/obis-status.1
man/man1/obis-sync.1
man/man1/obis.1
obis/__init__.py
obis/conftest.py
obis.egg-info/PKG-INFO
obis.egg-info/SOURCES.txt
obis.egg-info/dependency_links.txt
obis.egg-info/entry_points.txt
obis.egg-info/not-zip-safe
obis.egg-info/requires.txt
obis.egg-info/top_level.txt
obis/__pycache__/__init__.cpython-310.pyc
obis/dm/__init__.py
obis/dm/checksum.py
obis/dm/command_log.py
obis/dm/command_result.py
obis/dm/config.py
obis/dm/config_test.py
obis/dm/data_mgmt.py
obis/dm/data_mgmt_test.py
obis/dm/git-annex-attributes
obis/dm/git.py
obis/dm/repository_utils.py
obis/dm/utils.py
obis/dm/utils_test.py
obis/dm/.obis/config.json
obis/dm/__pycache__/__init__.cpython-310.pyc
obis/dm/__pycache__/checksum.cpython-310.pyc
obis/dm/__pycache__/command_log.cpython-310.pyc
obis/dm/__pycache__/command_result.cpython-310.pyc
obis/dm/__pycache__/config.cpython-310.pyc
obis/dm/__pycache__/data_mgmt.cpython-310.pyc
obis/dm/__pycache__/git.cpython-310.pyc
obis/dm/__pycache__/repository_utils.cpython-310.pyc
obis/dm/__pycache__/utils.cpython-310.pyc
obis/dm/commands/__init__.py
obis/dm/commands/addref.py
obis/dm/commands/clone.py
obis/dm/commands/collection.py
obis/dm/commands/download.py
obis/dm/commands/download_physical.py
obis/dm/commands/move.py
obis/dm/commands/object.py
obis/dm/commands/openbis_command.py
obis/dm/commands/openbis_command_test.py
obis/dm/commands/openbis_sync.py
obis/dm/commands/removeref.py
obis/dm/commands/search.py
obis/dm/commands/upload.py
obis/dm/commands/__pycache__/__init__.cpython-310.pyc
obis/dm/commands/__pycache__/addref.cpython-310.pyc
obis/dm/commands/__pycache__/clone.cpython-310.pyc
obis/dm/commands/__pycache__/collection.cpython-310.pyc
obis/dm/commands/__pycache__/download.cpython-310.pyc
