Metadata-Version: 2.1
Name: obis
Version: 0.4.7
Summary: Local data management with assistance from OpenBIS.
Home-page: https://sissource.ethz.ch/sispub/openbis/tree/master/app-openbis-command-line
Author: ID SIS • ETH Zürich
Author-email: openbis-support@id.ethz.ch
License: Apache Software License Version 2.0
Classifier: Programming Language :: Python :: 3
Classifier: License :: OSI Approved :: Apache Software License
Classifier: Operating System :: OS Independent
Requires-Python: >=3.3
License-File: LICENSE
